hydrotools/nwm_client/AzureFileCatalog.py
hydrotools/nwm_client/FileDownloader.py
hydrotools/nwm_client/GCPFileCatalog.py
hydrotools/nwm_client/HTTPFileCatalog.py
hydrotools/nwm_client/NWMClient.py
hydrotools/nwm_client/NWMClientDefaults.py
hydrotools/nwm_client/NWMFileCatalog.py
hydrotools/nwm_client/NWMFileClient.py
hydrotools/nwm_client/NWMFileProcessor.py
hydrotools/nwm_client/ParquetStore.py
hydrotools/nwm_client/UnitHandler.py
hydrotools/nwm_client/__init__.py
hydrotools/nwm_client/_version.py
hydrotools_nwm_client-9.1.1.dist-info/licenses/LICENSE
hydrotools_nwm_client-9.1.1.dist-info/licenses/NOTICE
hydrotools_nwm_client-9.1.1.dist-info/METADATA
hydrotools_nwm_client-9.1.1.dist-info/WHEEL
hydrotools_nwm_client-9.1.1.dist-info/top_level.txt
hydrotools_nwm_client-9.1.1.dist-info/RECORD
